dask_histogram/__init__.py
dask_histogram/bins.py
dask_histogram/boost.py
dask_histogram/config.py
dask_histogram/core.py
dask_histogram/histogram.yaml
dask_histogram/layers.py
dask_histogram/py.typed
dask_histogram/routines.py
dask_histogram/typing.py
dask_histogram/version.py
dask_histogram_sizeof/__init__.py
dask_histogram-2024.12.1.dist-info/METADATA
dask_histogram-2024.12.1.dist-info/WHEEL
dask_histogram-2024.12.1.dist-info/entry_points.txt
dask_histogram-2024.12.1.dist-info/licenses/LICENSE
dask_histogram-2024.12.1.dist-info/RECORD
